exif/__init__.py
exif/_app1_create.py
exif/_app1_metadata.py
exif/_constants.py
exif/_datatypes.py
exif/_image.py
exif/_utils.py
exif/ifd_tag/__init__.py
exif/ifd_tag/_ascii.py
exif/ifd_tag/_base.py
exif/ifd_tag/_byte.py
exif/ifd_tag/_exifversion.py
exif/ifd_tag/_long.py
exif/ifd_tag/_rational.py
exif/ifd_tag/_short.py
exif/ifd_tag/_slong.py
exif/ifd_tag/_srational.py
exif/ifd_tag/_sshort.py
exif/ifd_tag/_user_comment.py
exif/ifd_tag/_windows_xp.py
exif-1.6.1.dist-info/LICENSE
exif-1.6.1.dist-info/METADATA
exif-1.6.1.dist-info/WHEEL
exif-1.6.1.dist-info/top_level.txt
exif-1.6.1.dist-info/RECORD
