Metadata-Version: 2.1
Name: exif
Version: 1.6.1
Summary: Read and modify image EXIF metadata using Python.
Home-page: https://gitlab.com/TNThieding/exif
Author: Tyler N. Thieding
Author-email: python@thieding.com
Maintainer: Tyler N. Thieding
Maintainer-email: python@thieding.com
License: UNKNOWN
Download-URL: https://gitlab.com/TNThieding/exif
Platform: UNKNOWN
Classifier: Development Status :: 5 - Production/Stable
Classifier: Intended Audience :: Developers
Classifier: Intended Audience :: End Users/Desktop
Classifier: License :: OSI Approved :: MIT License
Classifier: Natural Language :: English
Classifier: Operating System :: OS Independent
Classifier: Programming Language :: Python :: 3
Classifier: Programming Language :: Python :: 3 :: Only
Classifier: Programming Language :: Python :: 3.7
Classifier: Programming Language :: Python :: 3.8
Classifier: Programming Language :: Python :: 3.9
Classifier: Programming Language :: Python :: 3.10
Classifier: Topic :: Multimedia :: Graphics :: Editors
Requires-Python: >=3.7
License-File: LICENSE
